{
    "type": "FeatureCollection",
    "features": [
      {
        "type": "Feature",
        "properties": {"name": "reg1"},
        "geometry": {
          "coordinates": [
            [
              [
                -71.28905619609387,
                42.53260696839013
              ],
              [
                -71.28905619609387,
                42.17328257325107
              ],
              [
                -70.8143786408113,
                42.17328257325107
              ],
              [
                -70.8143786408113,
                42.53260696839013
              ],
              [
                -71.28905619609387,
                42.53260696839013
              ]
            ]
          ],
          "type": "Polygon"
        }
      },
      {
        "type": "Feature",
        "properties": {"name": "reg2"},
        "geometry": {
          "coordinates": [
            [
              [
                -71.89097695658948,
                42.68166103166129
              ],
              [
                -71.89097695658948,
                42.53687163947987
              ],
              [
                -71.32957470703374,
                42.53687163947987
              ],
              [
                -71.32957470703374,
                42.68166103166129
              ],
              [
                -71.89097695658948,
                42.68166103166129
              ]
            ]
          ],
          "type": "Polygon"
        }
      },
      {
        "type": "Feature",
        "properties": {"name": "reg3"},
        "geometry": {
          "coordinates": [
            [
              [
                -71.89676753015678,
                42.5155248182777
              ],
              [
                -71.89676753015678,
                42.10033167898368
              ],
              [
                -71.31800040562882,
                42.10033167898368
              ],
              [
                -71.31800040562882,
                42.5155248182777
              ],
              [
                -71.89676753015678,
                42.5155248182777
              ]
            ]
          ],
          "type": "Polygon"
        }
      },
      {
        "type": "Feature",
        "properties": {"name": "reg4"},
        "geometry": {
          "coordinates": [
            [
              [
                -71.26590750633063,
                42.6817103455499
              ],
              [
                -71.26590750633063,
                42.5539388610797
              ],
              [
                -70.65807974374941,
                42.5539388610797
              ],
              [
                -70.65807974374941,
                42.6817103455499
              ],
              [
                -71.26590750633063,
                42.6817103455499
              ]
            ]
          ],
          "type": "Polygon"
        }
      },
      {
        "type": "Feature",
        "properties": {"name": "reg5"},
        "geometry": {
          "coordinates": [
            [
              [
                -74.40139954367129,
                41.98023048400054
              ],
              [
                -74.40139954367129,
                41.617631118140906
              ],
              [
                -73.53456658319624,
                41.617631118140906
              ],
              [
                -73.53456658319624,
                41.98023048400054
              ],
              [
                -74.40139954367129,
                41.98023048400054
              ]
            ]
          ],
          "type": "Polygon"
        }
      },
      {
        "type": "Feature",
        "properties": {"name": "reg6"},
        "geometry": {
          "coordinates": [
            [
              [
                -74.39098556270706,
                41.59169519603057
              ],
              [
                -74.39098556270706,
                41.213924159257516
              ],
              [
                -73.56942900194078,
                41.213924159257516
              ],
              [
                -73.56942900194078,
                41.59169519603057
              ],
              [
                -74.39098556270706,
                41.59169519603057
              ]
            ]
          ],
          "type": "Polygon"
        }
      },
      {
        "type": "Feature",
        "properties": {"name": "reg7"},
        "geometry": {
          "coordinates": [
            [
              [
                -74.39689641665848,
                41.18787172684546
              ],
              [
                -74.39689641665848,
                41.01758824762581
              ],
              [
                -73.74902972631182,
                41.01758824762581
              ],
              [
                -73.74902972631182,
                41.18787172684546
              ],
              [
                -74.39689641665848,
                41.18787172684546
              ]
            ]
          ],
          "type": "Polygon"
        }
      },
      {
        "type": "Feature",
        "properties": {"name": "reg8"},
        "geometry": {
          "coordinates": [
            [
              [
                -73.45885400202248,
                41.988748757313715
              ],
              [
                -73.45885400202248,
                41.45718103314124
              ],
              [
                -71.80420849148713,
                41.45718103314124
              ],
              [
                -71.80420849148713,
                41.988748757313715
              ],
              [
                -73.45885400202248,
                41.988748757313715
              ]
            ]
          ],
          "type": "Polygon"
        }
      },
      {
        "type": "Feature",
        "properties": {"name": "reg9"},
        "geometry": {
          "coordinates": [
            [
              [
                -73.51144245771715,
                41.4356484714458
              ],
              [
                -73.51144245771715,
                41.18326567271987
              ],
              [
                -72.87508456530098,
                41.18326567271987
              ],
              [
                -72.87508456530098,
                41.4356484714458
              ],
              [
                -73.51144245771715,
                41.4356484714458
              ]
            ]
          ],
          "type": "Polygon"
        }
      },
      {
        "type": "Feature",
        "properties": {"name": "reg10"},
        "geometry": {
          "coordinates": [
            [
              [
                -72.81711001307004,
                41.43118712107642
              ],
              [
                -72.81711001307004,
                41.344261697446626
              ],
              [
                -71.83894462912419,
                41.344261697446626
              ],
              [
                -71.83894462912419,
                41.43118712107642
              ],
              [
                -72.81711001307004,
                41.43118712107642
              ]
            ]
          ],
          "type": "Polygon"
        }
      },
      {
        "type": "Feature",
        "properties": {"name": "reg11"},
        "geometry": {
          "coordinates": [
            [
              [
                -74.0123151089901,
                40.69503615660102
              ],
              [
                -74.0123151089901,
                40.594872445451216
              ],
              [
                -73.35775334198007,
                40.594872445451216
              ],
              [
                -73.35775334198007,
                40.69503615660102
              ],
              [
                -74.0123151089901,
                40.69503615660102
              ]
            ]
          ],
          "type": "Polygon"
        }
      },
      {
        "type": "Feature",
        "properties": {"name": "reg12"},
        "geometry": {
          "coordinates": [
            [
              [
                -73.72991903843511,
                40.87488046652979
              ],
              [
                -73.72991903843511,
                40.71306141546572
              ],
              [
                -73.3682904608808,
                40.71306141546572
              ],
              [
                -73.3682904608808,
                40.87488046652979
              ],
              [
                -73.72991903843511,
                40.87488046652979
              ]
            ]
          ],
          "type": "Polygon"
        }
      },
      {
        "type": "Feature",
        "properties": {"name": "reg13"},
        "geometry": {
          "coordinates": [
            [
              [
                -73.74834593041925,
                40.71507447119407
              ],
              [
                -73.74834593041925,
                40.77703649429358
              ],
              [
                -73.92785066971066,
                40.77703649429358
              ],
              [
                -73.92785066971066,
                40.71507447119407
              ],
              [
                -73.74834593041925,
                40.71507447119407
              ]
            ]
          ],
          "type": "Polygon"
        }
      },
      {
        "type": "Feature",
        "properties": {"name": "reg14"},
        "geometry": {
          "coordinates": [
            [
              [
                -74.42338969620778,
                40.93103536467015
              ],
              [
                -74.42338969620778,
                40.729032681911804
              ],
              [
                -74.05456561478073,
                40.729032681911804
              ],
              [
                -74.05456561478073,
                40.93103536467015
              ],
              [
                -74.42338969620778,
                40.93103536467015
              ]
            ]
          ],
          "type": "Polygon"
        }
      },
      {
        "type": "Feature",
        "properties": {"name": "reg15"},
        "geometry": {
          "coordinates": [
            [
              [
                -73.73781546191285,
                40.93474516340763
              ],
              [
                -73.90665395177423,
                40.932804754222616
              ],
              [
                -73.9568761247932,
                40.82898820314281
              ],
              [
                -74.00440068516566,
                40.757040908097935
              ],
              [
                -73.99912975567821,
                40.70503185178768
              ],
              [
                -73.94632698522814,
                40.7790347833583
              ],
              [
                -73.81172636401634,
                40.81299540480819
              ],
              [
                -73.73781546191285,
                40.93474516340763
              ]
            ]
          ],
          "type": "Polygon"
        }
      },
      {
        "type": "Feature",
        "properties": {"name": "reg16"},
        "geometry": {
          "coordinates": [
            [
              [
                -74.42114038214788,
                40.71120461797432
              ],
              [
                -74.42114038214788,
                40.50662746320674
              ],
              [
                -74.03610344943714,
                40.50662746320674
              ],
              [
                -74.03610344943714,
                40.71120461797432
              ],
              [
                -74.42114038214788,
                40.71120461797432
              ]
            ]
          ],
          "type": "Polygon"
        }
      }
    ]
  }
